BUCTOJ/AutoGetAndSubmit.py
BUCTOJ/Config.py
BUCTOJ/DownloadAllCodes.py
BUCTOJ/EditingAProbem.py
BUCTOJ/FromPidToChar.py
BUCTOJ/GetASourceCodeAndChange.py
BUCTOJ/GetContestProblemList.py
BUCTOJ/Login.py
BUCTOJ/SubmitOneCode.py
BUCTOJ/__init__.py
BUCTOJ-0.3.8.1.dist-info/LICENSE
BUCTOJ-0.3.8.1.dist-info/METADATA
BUCTOJ-0.3.8.1.dist-info/WHEEL
BUCTOJ-0.3.8.1.dist-info/top_level.txt
BUCTOJ-0.3.8.1.dist-info/RECORD
