Metadata-Version: 2.1
Name: BUCTOJ
Version: 0.3.8.1
Summary: 用Python玩转北化OJ平台
Home-page: https://github.com/LetMeFly666/BUCTOJ
Author: LetMeFly
Author-email: Tisfy@qq.com
License: Apache License
Project-URL: Bug Tracker, https://github.com/LetMeFly666/BUCTOJ/issues
Project-URL: 在线文档, https://buctoj.readthedocs.io
Platform: all
Classifier: Intended Audience :: Developers
Classifier: Operating System :: OS Independent
Classifier: Natural Language :: Chinese (Simplified)
Classifier: Programming Language :: Python
Classifier: Programming Language :: Python :: 2
Classifier: Programming Language :: Python :: 2.7
Classifier: Programming Language :: Python :: 3
Classifier: Programming Language :: Python :: 3.5
Classifier: Programming Language :: Python :: 3.6
Classifier: Programming Language :: Python :: 3.7
Classifier: Programming Language :: Python :: 3.8
Classifier: Programming Language :: Python :: 3.9
Classifier: Topic :: Software Development :: Libraries
License-File: LICENSE
Requires-Dist: requests >=1.0.0
Requires-Dist: lxml >=2.0
Requires-Dist: beautifulsoup4 >=4.0.1
